odoo8_addon_test_base_import_async-8.0.1.0.0-py2.7-nspkg.pth
odoo_addons/test_base_import_async/__openerp__.py
odoo_addons/test_base_import_async/__init__.py
odoo_addons/test_base_import_async/tests/test_base_import_async.py
odoo_addons/test_base_import_async/tests/__init__.py
odoo_addons/test_base_import_async/tests/account.move.csv
odoo8_addon_test_base_import_async-8.0.1.0.0.dist-info/top_level.txt
odoo8_addon_test_base_import_async-8.0.1.0.0.dist-info/WHEEL
odoo8_addon_test_base_import_async-8.0.1.0.0.dist-info/RECORD
odoo8_addon_test_base_import_async-8.0.1.0.0.dist-info/metadata.json
odoo8_addon_test_base_import_async-8.0.1.0.0.dist-info/DESCRIPTION.rst
odoo8_addon_test_base_import_async-8.0.1.0.0.dist-info/METADATA
odoo8_addon_test_base_import_async-8.0.1.0.0.dist-info/namespace_packages.txt
